MANIFEST.in
README
cubicweb-vcsfile.spec
setup.py
tox.ini
cubicweb_vcsfile/__init__.py
cubicweb_vcsfile/__pkginfo__.py
cubicweb_vcsfile/bridge.py
cubicweb_vcsfile/ccplugin.py
cubicweb_vcsfile/docparser.py
cubicweb_vcsfile/hooks.py
cubicweb_vcsfile/queries.py
cubicweb_vcsfile/schema.py
cubicweb_vcsfile/site_cubicweb.py
cubicweb_vcsfile/sobjects.py
cubicweb_vcsfile/testutils.py
cubicweb_vcsfile.egg-info/PKG-INFO
cubicweb_vcsfile.egg-info/SOURCES.txt
cubicweb_vcsfile.egg-info/dependency_links.txt
cubicweb_vcsfile.egg-info/entry_points.txt
cubicweb_vcsfile.egg-info/not-zip-safe
cubicweb_vcsfile.egg-info/requires.txt
cubicweb_vcsfile.egg-info/top_level.txt
cubicweb_vcsfile/entities/__init__.py
cubicweb_vcsfile/entities/adapters.py
cubicweb_vcsfile/i18n/en.po
cubicweb_vcsfile/i18n/es.po
cubicweb_vcsfile/i18n/fr.po
cubicweb_vcsfile/migration/0.6.0_Any.py
cubicweb_vcsfile/migration/0.7.0_Any.py
cubicweb_vcsfile/migration/0.9.0_Any.py
cubicweb_vcsfile/migration/1.0.0_Any.py
cubicweb_vcsfile/migration/1.0.13_Any.py
cubicweb_vcsfile/migration/1.11.0_Any.py
cubicweb_vcsfile/migration/1.13.0_Any.py
cubicweb_vcsfile/migration/1.15.0_Any.py
cubicweb_vcsfile/migration/1.2.0_Any.py
cubicweb_vcsfile/migration/1.3.0_Any.py
cubicweb_vcsfile/migration/1.4.0_Any.py
cubicweb_vcsfile/migration/1.4.1_Any.py
cubicweb_vcsfile/migration/1.6.0_Any.py
cubicweb_vcsfile/migration/1.6.1_Any.py
cubicweb_vcsfile/migration/1.6.2_Any.py
cubicweb_vcsfile/migration/1.7.0_Any.py
cubicweb_vcsfile/migration/1.7.3_Any.py
cubicweb_vcsfile/migration/1.8.3_Any.py
cubicweb_vcsfile/migration/1.8.5_Any.py
cubicweb_vcsfile/migration/1.9.2_Any.py
cubicweb_vcsfile/migration/1.9.4_Any.py
cubicweb_vcsfile/migration/2.0.0_Any.py
cubicweb_vcsfile/migration/2.4.0_Any.py
cubicweb_vcsfile/migration/postcreate.py
cubicweb_vcsfile/scripts/cleanup_repo_cache.py
cubicweb_vcsfile/scripts/hgnotifhook.py
cubicweb_vcsfile/views/__init__.py
cubicweb_vcsfile/views/actions.py
cubicweb_vcsfile/views/facets.py
cubicweb_vcsfile/views/forms.py
cubicweb_vcsfile/views/primary.py
debian/changelog
debian/compat
debian/control
debian/copyright
debian/rules
test/test_vcsfile.py
test/unittest_entities.py
test/unittest_obsolescence.py
test/unittest_sobjects.py
test/unittest_vcssource.py
test/unittest_views.py
