Metadata-Version: 1.1
Name: cubicweb-vcsfile
Version: 2.5.0
Summary: component to integrate version control systems data into the CubicWeb framework
Home-page: http://www.cubicweb.org/project/cubicweb-vcsfile
Author: Logilab
Author-email: contact@logilab.fr
License: LGPL
Platform: UNKNOWN
Classifier: Environment :: Web Environment
Classifier: Framework :: CubicWeb
Classifier: Programming Language :: Python
Classifier: Programming Language :: JavaScript
